bplz/__init__.py
bplz/__main__.py
bplz/bplz.py
bplz/geckodriver.exe
bplz-0.0.22.dist-info/LICENSE
bplz-0.0.22.dist-info/METADATA
bplz-0.0.22.dist-info/WHEEL
bplz-0.0.22.dist-info/entry_points.txt
bplz-0.0.22.dist-info/top_level.txt
bplz-0.0.22.dist-info/RECORD
