Metadata-Version: 2.1
Name: bplz
Version: 0.0.22
Summary: http://www.giseden.xyz/?p=324
Home-page: https://github.com/tom110/bplz
Author: tom
Author-email: tomyeying@gmail.com
License: UNKNOWN
Platform: UNKNOWN
Classifier: Programming Language :: Python :: 3
Classifier: License :: OSI Approved :: MIT License
Classifier: Operating System :: OS Independent
Requires-Python: >=3.6
Requires-Dist: bs4
Requires-Dist: selenium
Requires-Dist: psutil
